{
    "954-111-1234": {
        "Order": "543",
        "Unit": "XC17-024-230 ic",
        "Price": "$2,033",
        "Status": "Shipped"
    },
    "954-222-2345": [
        {
            "Order": "654",
            "Unit": "XC17-024-230 ic",
            "Price": "$2,033",
            "Status": "Shipped"
        },
        {
            "Order": "785",
            "Unit": "XC17-024-230 ic",
            "Price": "$2,033",
            "Status": "In Process"
        },
        {
            "Order": "123",
            "Unit": "XC17-024-230 ic",
            "Price": "$2,033",
            "Status": "Delivered"
        }
    ]
}